<?xml version="1.0" encoding="UTF-8"?><record_update table="catalog_ui_policy_action">
    <catalog_ui_policy_action action="INSERT_OR_UPDATE">
        <catalog_item display_value="Submit a Mobile Request">7d453b461b801910d18fca246b4bcbdf</catalog_item>
        <catalog_variable>IO:5f0cb34e1b801910d18fca246b4bcbdc</catalog_variable>
        <cleared>false</cleared>
        <disabled>ignore</disabled>
        <field/>
        <mandatory>ignore</mandatory>
        <order>100</order>
        <sys_class_name>catalog_ui_policy_action</sys_class_name>
        <sys_created_by>eugene.sikorski</sys_created_by>
        <sys_created_on>2022-08-06 03:19:14</sys_created_on>
        <sys_id>6b8296c31b8595500931a977b04bcbf4</sys_id>
        <sys_mod_count>0</sys_mod_count>
        <sys_name>zip_code</sys_name>
        <sys_package display_value="VMox Integration" source="x_cslb_vmox_integr">783537461b801910d18fca246b4bcb02</sys_package>
        <sys_policy/>
        <sys_scope display_value="VMox Integration">783537461b801910d18fca246b4bcb02</sys_scope>
        <sys_update_name>catalog_ui_policy_action_6b8296c31b8595500931a977b04bcbf4</sys_update_name>
        <sys_updated_by>eugene.sikorski</sys_updated_by>
        <sys_updated_on>2022-08-06 03:19:14</sys_updated_on>
        <table/>
        <ui_policy display_value="If Order Type is Support display multi row text box">9691d6031b8595500931a977b04bcb5c</ui_policy>
        <variable>zip_code</variable>
        <variable_set/>
        <visible>false</visible>
    </catalog_ui_policy_action>
</record_update>
