<?xml version="1.0" encoding="UTF-8"?><record_update table="sc_cat_item">
    <sc_cat_item action="INSERT_OR_UPDATE">
        <access_type>restricted</access_type>
        <active>true</active>
        <availability>on_desktop</availability>
        <billable>false</billable>
        <category display_value="Equipment">e8edba3a1b1c341077fc6246b04bcbbb</category>
        <checked_out/>
        <cost>0</cost>
        <custom_cart/>
        <delivery_plan/>
        <delivery_plan_script/>
        <delivery_time>1970-01-03 00:00:00</delivery_time>
        <description/>
        <display_price_property>non_zero</display_price_property>
        <entitlement_script/>
        <flow_designer_flow display_value="VMox Logic Flow">e52c3da21bc45910d18fca246b4bcb20</flow_designer_flow>
        <group/>
        <hide_sp>false</hide_sp>
        <icon/>
        <ignore_price>true</ignore_price>
        <image/>
        <location/>
        <mandatory_attachment>false</mandatory_attachment>
        <meta>mobile, mobile, mobile, vmox, vmox, vmox, request</meta>
        <mobile_hide_price>false</mobile_hide_price>
        <mobile_picture/>
        <mobile_picture_type>use_desktop_picture</mobile_picture_type>
        <model/>
        <name>Submit a Mobile Request</name>
        <no_attachment_v2>false</no_attachment_v2>
        <no_cart>false</no_cart>
        <no_cart_v2>false</no_cart_v2>
        <no_delivery_time_v2>true</no_delivery_time_v2>
        <no_order>false</no_order>
        <no_order_now>false</no_order_now>
        <no_proceed_checkout>false</no_proceed_checkout>
        <no_quantity>false</no_quantity>
        <no_quantity_v2>true</no_quantity_v2>
        <no_search>false</no_search>
        <no_wishlist_v2>false</no_wishlist_v2>
        <omit_price>false</omit_price>
        <order>0</order>
        <ordered_item_link/>
        <owner display_value="Brandon Vandermark">4ddd16e81b4855100931a977b04bcb82</owner>
        <picture/>
        <preview>JavaScript: popupOpenStandard("com.glideapp.servicecatalog_cat_item_view.do?v=1&amp;sysparm_id=7d453b461b801910d18fca246b4bcbdf&amp;sysparm_preview=true", "summary");</preview>
        <price>0</price>
        <published_ref/>
        <recurring_frequency/>
        <recurring_price>0</recurring_price>
        <request_method/>
        <roles/>
        <sc_catalogs>e0d08b13c3330100c8b837659bba8fb4</sc_catalogs>
        <sc_ic_item_staging/>
        <sc_ic_version/>
        <sc_template/>
        <short_description/>
        <show_variable_help_on_load>false</show_variable_help_on_load>
        <start_closed>false</start_closed>
        <state/>
        <sys_class_name>sc_cat_item</sys_class_name>
        <sys_created_by>Brandon.Vandermark</sys_created_by>
        <sys_created_on>2022-06-14 14:54:43</sys_created_on>
        <sys_id>7d453b461b801910d18fca246b4bcbdf</sys_id>
        <sys_mod_count>5</sys_mod_count>
        <sys_name>Submit a Mobile Request</sys_name>
        <sys_package display_value="VMox Integration" source="x_cslb_vmox_integr">783537461b801910d18fca246b4bcb02</sys_package>
        <sys_policy/>
        <sys_scope display_value="VMox Integration">783537461b801910d18fca246b4bcb02</sys_scope>
        <sys_update_name>sc_cat_item_7d453b461b801910d18fca246b4bcbdf</sys_update_name>
        <sys_updated_by>eugene.sikorski</sys_updated_by>
        <sys_updated_on>2022-08-05 16:32:27</sys_updated_on>
        <template/>
        <template_manager_roles/>
        <type>item</type>
        <u_approval_level_2_type/>
        <u_approval_level_3_type/>
        <u_bypass_line_manager_approval>true</u_bypass_line_manager_approval>
        <u_fulfillment_group_1/>
        <u_fulfillment_group_2/>
        <u_fulfillment_group_3/>
        <u_fulfillment_group_4/>
        <u_group_approval_level_2/>
        <u_group_approval_level_3/>
        <u_knowledge_article/>
        <u_service_group_owner/>
        <u_service_owner/>
        <u_single_approver_level_2/>
        <u_single_approver_level_3/>
        <u_task_1_summary/>
        <u_task_2_summary/>
        <u_task_3_summary/>
        <u_task_4_summary/>
        <u_task_sla/>
        <use_sc_layout>true</use_sc_layout>
        <vendor/>
        <visible_bundle>true</visible_bundle>
        <visible_guide>true</visible_guide>
        <visible_standalone>true</visible_standalone>
        <workflow/>
    </sc_cat_item>
    <sys_translated_text action="delete_multiple" query="documentkey=7d453b461b801910d18fca246b4bcbdf"/>
    <fx_price action="delete_multiple" query="id=7d453b461b801910d18fca246b4bcbdf"/>
    <fx_price action="INSERT_OR_UPDATE">
        <amount>0</amount>
        <currency display_value="USD">USD</currency>
        <field>price</field>
        <id>7d453b461b801910d18fca246b4bcbdf</id>
        <parent/>
        <reference_amount>0</reference_amount>
        <reference_currency display_value="USD">USD</reference_currency>
        <sys_created_by>Brandon.Vandermark</sys_created_by>
        <sys_created_on>2022-06-14 14:54:44</sys_created_on>
        <sys_id>3c8573861b801910d18fca246b4bcb8b</sys_id>
        <sys_mod_count>0</sys_mod_count>
        <sys_updated_by>Brandon.Vandermark</sys_updated_by>
        <sys_updated_on>2022-06-14 14:54:44</sys_updated_on>
        <table>sc_cat_item</table>
        <type>calculated</type>
    </fx_price>
    <fx_price action="INSERT_OR_UPDATE">
        <amount>0</amount>
        <currency display_value="USD">USD</currency>
        <field>recurring_price</field>
        <id>7d453b461b801910d18fca246b4bcbdf</id>
        <parent/>
        <reference_amount>0</reference_amount>
        <reference_currency display_value="USD">USD</reference_currency>
        <sys_created_by>Brandon.Vandermark</sys_created_by>
        <sys_created_on>2022-06-14 14:54:44</sys_created_on>
        <sys_id>fc8573861b801910d18fca246b4bcb8c</sys_id>
        <sys_mod_count>0</sys_mod_count>
        <sys_updated_by>Brandon.Vandermark</sys_updated_by>
        <sys_updated_on>2022-06-14 14:54:44</sys_updated_on>
        <table>sc_cat_item</table>
        <type>calculated</type>
    </fx_price>
</record_update>
